mvg/__init__.py
mvg/analysis_classes.py
mvg/exceptions.py
mvg/http_client.py
mvg/mvg.py
mvg/plotting.py
mvg/features/__init__.py
mvg/features/analysis.py
mvg/features/blacksheep.py
mvg/features/kpidemo.py
mvg/features/label_propagation.py
mvg/features/modeid.py
mvg/utils/__init__.py
mvg/utils/response_processing.py
va_mvg-0.15.0.dist-info/LICENSE
va_mvg-0.15.0.dist-info/METADATA
va_mvg-0.15.0.dist-info/WHEEL
va_mvg-0.15.0.dist-info/top_level.txt
va_mvg-0.15.0.dist-info/RECORD
