Metadata-Version: 2.1
Name: va-mvg
Version: 0.15.0
Summary: MultiViz Analytics Engine library
Home-page: https://github.com/vikinganalytics/mvg
Author: Viking Analytics
Author-email: info@vikinganalytics.se
License: LICENSE
Classifier: License :: OSI Approved :: Apache Software License
Classifier: Operating System :: OS Independent
Classifier: Programming Language :: Python :: 3.6
Classifier: Programming Language :: Python :: 3.7
Classifier: Programming Language :: Python :: 3.8
Classifier: Programming Language :: Python :: 3.9
Classifier: Programming Language :: Python :: 3.10
Classifier: Programming Language :: Python :: 3.11
Requires-Python: >=3.6
License-File: LICENSE
Requires-Dist: pandas <=2.0.3,>=1.1.5
Requires-Dist: requests <=2.31.0,>=2.27.1
Requires-Dist: numpy <=1.24.1,>=1.19.5
Requires-Dist: semver <=3.0.1,>=2.13.0
Requires-Dist: matplotlib <=3.7.2,>=3.3.4
Requires-Dist: tabulate <=0.9.0,>=0.8.10
Requires-Dist: pydantic <=1.10.11,>=1.9.2
